see/__init__.py
see/client.py
see/exceptions.py
see/http_client.py
see/py.typed
see/version.py
see/api/base.py
see/api/file.py
see/api/text.py
see/api/url.py
see/models/__init__.py
see/models/common.py
see/models/file.py
see/models/text.py
see/models/url.py
see_sdk-1.1.1.dist-info/licenses/LICENSE
see_sdk-1.1.1.dist-info/METADATA
see_sdk-1.1.1.dist-info/WHEEL
see_sdk-1.1.1.dist-info/top_level.txt
see_sdk-1.1.1.dist-info/RECORD
