Metadata-Version: 2.4
Name: see-sdk
Version: 1.1.1
Summary: A modern Python SDK for SEE Content Sharing services (Short URL, Text, File, etc.)
Author-email: mingcheng <mingcheng@apache.org>, showfom <showfom@s.ee>
License: MIT
Project-URL: Homepage, https://s.ee/
Project-URL: Documentation, https://s.ee/docs/developers/
Project-URL: Repository, https://github.com/sdotee/sdk.py
Project-URL: Issues, https://github.com/sdotee/sdk.py/issues
Keywords: sdk,api,async,python,url-shortener,text-sharing,file-sharing
Classifier: Development Status :: 4 - Beta
Classifier: Intended Audience :: Developers
Classifier: License :: OSI Approved :: MIT License
Classifier: Programming Language :: Python :: 3
Classifier: Programming Language :: Python :: 3.11
Classifier: Programming Language :: Python :: 3.12
Classifier: Programming Language :: Python :: 3.13
Classifier: Typing :: Typed
Classifier: Framework :: AsyncIO
Requires-Python: >=3.11
License-File: LICENSE
Requires-Dist: httpx>=0.27.0
Provides-Extra: dev
Requires-Dist: pytest>=8.0.0; extra == "dev"
Requires-Dist: pytest-asyncio>=0.23.0; extra == "dev"
Requires-Dist: pytest-cov>=4.1.0; extra == "dev"
Requires-Dist: pytest-mock>=3.12.0; extra == "dev"
Requires-Dist: black>=24.0.0; extra == "dev"
Requires-Dist: ruff>=0.3.0; extra == "dev"
Requires-Dist: mypy>=1.8.0; extra == "dev"
Requires-Dist: pre-commit>=3.6.0; extra == "dev"
Requires-Dist: build>=1.0.0; extra == "dev"
Requires-Dist: twine>=4.0.0; extra == "dev"
Provides-Extra: docs
Requires-Dist: sphinx>=7.2.0; extra == "docs"
Requires-Dist: sphinx-rtd-theme>=2.0.0; extra == "docs"
Dynamic: license-file
